alumath_matmult/__init__.py
alumath_matmult/math.py
alumath_matmult-0.1.0.dist-info/METADATA
alumath_matmult-0.1.0.dist-info/WHEEL
alumath_matmult-0.1.0.dist-info/top_level.txt
alumath_matmult-0.1.0.dist-info/RECORD
