Metadata-Version: 2.4
Name: alumath-matmult
Version: 0.1.0
Summary: A simple Python package for matrix operations
Home-page: https://github.com/LaurelleJinelle/alumath_matmult.git
Author: Group 16
Author-email: j.nformi1@alustudent.com
Classifier: Programming Language :: Python :: 3
Classifier: Operating System :: OS Independent
Requires-Python: >=3.6
Dynamic: author
Dynamic: author-email
Dynamic: classifier
Dynamic: description-content-type
Dynamic: home-page
Dynamic: requires-python
Dynamic: summary
